README.md
setup.py
pytooth/__init__.py
pytooth/bluetooth_base.py
pytooth/bluetooth_device.py
pytooth/bluetooth_manager.py
pytooth/constants.py
pytooth/exceptions.py
pytooth.egg-info/PKG-INFO
pytooth.egg-info/SOURCES.txt
pytooth.egg-info/dependency_links.txt
pytooth.egg-info/top_level.txt