Metadata-Version: 2.1
Name: pytooth
Version: 0.1.0
Summary: A better PyBluez
Home-page: https://github.com/paysonwallach/pytooth
Author: Payson Wallach
Author-email: paysonwallach@icloud.com
License: UNKNOWN
Platform: UNKNOWN
Classifier: Topic :: System :: Networking
Classifier: Operating System :: POSIX :: Linux
